fmc_report/__init__.py
fmc_report/__main__.py
fmc_report/accessRules.py
fmc_report/app.py
fmc_report/fmc_connect.py
fmc_report/static/css/overlay.css
fmc_report/static/js/tables-loading.js
fmc_report/templates/index.html
fmc_report/templates/login.html
fmc_report/templates/prefilter_table.html
fmc_report/templates/tables.html
fmc_report/templates/vpn.html
fmc_report/templates/error_pages/500.html
fmc_report-3.0.0.dist-info/licenses/LICENSE
fmc_report-3.0.0.dist-info/METADATA
fmc_report-3.0.0.dist-info/WHEEL
fmc_report-3.0.0.dist-info/top_level.txt
fmc_report-3.0.0.dist-info/RECORD
