Metadata-Version: 2.4
Name: fmc_report
Version: 3.0.0
Summary: This tool is intended to export access lists via API from the FMC.
Author-email: Timo Riedinger <timo.riedinger@bechtle.com>
License:  The MIT License (MIT)
Keywords: FirePowerManagementCenter,FMC
Classifier: Programming Language :: Python :: 3.13
Requires-Python: >=3.13.0
License-File: LICENSE
Requires-Dist: blinker==1.9.0
Requires-Dist: certifi==2025.7.14
Requires-Dist: charset-normalizer==3.4.2
Requires-Dist: click==8.2.1
Requires-Dist: decorator==5.2.1
Requires-Dist: fireREST==1.2.3
Requires-Dist: Flask==3.1.1
Requires-Dist: idna==3.10
Requires-Dist: itsdangerous==2.2.0
Requires-Dist: Jinja2==3.1.6
Requires-Dist: MarkupSafe==3.0.2
Requires-Dist: packaging==25.0
Requires-Dist: pkginfo>=1.12.1.2
Requires-Dist: py==1.11.0
Requires-Dist: python-dotenv==1.1.1
Requires-Dist: requests==2.32.4
Requires-Dist: retry==0.9.2
Requires-Dist: simplejson==3.20.1
Requires-Dist: twine>=6.1.0
Requires-Dist: urllib3==2.5.0
Requires-Dist: Werkzeug==3.1.3
Dynamic: license-file
